ArubaOS_XML_API/__init__.py
ArubaOS_XML_API/aruba_cmd.py
ArubaOS_XML_API-0.2.dist-info/LICENSE.txt
ArubaOS_XML_API-0.2.dist-info/METADATA
ArubaOS_XML_API-0.2.dist-info/RECORD
ArubaOS_XML_API-0.2.dist-info/WHEEL
ArubaOS_XML_API-0.2.dist-info/top_level.txt
